security/__init__.py
security/admin.py
security/auth.py
security/forms.py
security/middleware.py
security/models.py
security/password_expiry.py
security/urls.py
security/views.py
security/auth_throttling/__init__.py
security/auth_throttling/views.py
security/migrations/0001_initial.py
security/migrations/__init__.py
security/south_migrations/0001_initial.py
security/south_migrations/0002_allow_null_password_expiry.py
security/south_migrations/0003_auto__add_cspreport.py
security/south_migrations/__init__.py
django_security_2.0-1.0.1.dist-info/LICENSE.txt
django_security_2.0-1.0.1.dist-info/METADATA
django_security_2.0-1.0.1.dist-info/WHEEL
django_security_2.0-1.0.1.dist-info/top_level.txt
django_security_2.0-1.0.1.dist-info/RECORD
