Metadata-Version: 2.1
Name: django-security-2.0
Version: 1.0.1
Summary: A collection of tools to help secure a Django project. update 2.1.4. mod for pwdExpiry
Home-page: https://github.com/dai-ictgeo/django-security
Maintainer: T
Maintainer-email: 
License: UNKNOWN
Platform: UNKNOWN
Classifier: Framework :: Django
Classifier: Framework :: Django :: 1.8
Classifier: Framework :: Django :: 1.9
Classifier: Framework :: Django :: 1.10
Classifier: Framework :: Django :: 1.11
Classifier: Environment :: Web Environment
Classifier: Programming Language :: Python
Classifier: Programming Language :: Python :: 2
Classifier: Programming Language :: Python :: 2.7
Classifier: Programming Language :: Python :: 3
Classifier: Programming Language :: Python :: 3.6
Classifier: Intended Audience :: Developers
Classifier: Operating System :: OS Independent
Classifier: License :: OSI Approved :: BSD License
Classifier: Topic :: Software Development :: Libraries :: Python Modules
Classifier: Topic :: Security
Requires-Dist: django (>=1.8)
Requires-Dist: ua-parser (==0.7.1)
